tradesim/__init__.py
tradesim/app.py
tradesim/defaults.py
tradesim/Components/__init__.py
tradesim/Components/candlestick_charts.py
tradesim/Components/graph.py
tradesim/Components/home.py
tradesim/Components/news.py
tradesim/Components/portfolio.py
tradesim/Components/requests.py
tradesim/Layouts/__init__.py
tradesim/Layouts/dashboard.py
tradesim/Layouts/home.py
tradesim/Locales/__init__.py
tradesim/Locales/en.py
tradesim/Locales/fr.py
tradesim/Setup/__init__.py
tradesim/Setup/analyze.ipynb
tradesim/Setup/download_market_data.py
tradesim/States/__init__.py
tradesim/States/import_data.py
tradesim/States/save_state.py
tradesim/assets/10_style.css
tradesim/assets/20_dashboard.css
tradesim/assets/20_home.css
tradesim/pages/__init__.py
tradesim/pages/dashboard.py
tradesim/pages/home.py
tradesim-0.2.2.data/scripts/tradesim
tradesim-0.2.2.dist-info/LICENSE
tradesim-0.2.2.dist-info/METADATA
tradesim-0.2.2.dist-info/WHEEL
tradesim-0.2.2.dist-info/top_level.txt
tradesim-0.2.2.dist-info/RECORD
