Metadata-Version: 2.1
Name: tradesim
Version: 0.2.2
Summary: A stock market site simulator for collecting data on stocks carried out by the trader.
Home-page: https://github.com/kelhad00/trading_simulator
Download-URL: https://github.com/kelhad00/trading_simulator/releases
Author: Gatien VILAIN, Capucine FOUILLARD, Paul HERBEAU, Kevin EL HADDAD
Author-email: kevin.elhaddad@umons.ac.be, gatien.vilain@outlook.fr, capucine.fouillard@student.junia.com, paul.herbeau01@gmail.com
License: Apache 2.0
Project-URL: Source, https://github.com/kelhad00/trading_simulator
Project-URL: Bug Tracker, https://github.com/kelhad00/trading_simulator/issues
Classifier: Development Status :: 4 - Beta
Classifier: Environment :: Web Environment
Classifier: Framework :: Dash
Classifier: Framework :: Flask
Classifier: Intended Audience :: Education
Classifier: Intended Audience :: Financial and Insurance Industry
Classifier: Intended Audience :: Science/Research
Classifier: Programming Language :: Python :: 3
Classifier: Programming Language :: Python :: 3.10
Classifier: Operating System :: OS Independent
Classifier: License :: OSI Approved :: Apache Software License
Classifier: Topic :: Scientific/Engineering
Requires-Python: ==3.10.*
License-File: LICENSE
Requires-Dist: dash ==2.10.2
Requires-Dist: pandas ==2.0.2
Provides-Extra: extra
Requires-Dist: yahooquery ==2.3.1 ; extra == 'extra'
Requires-Dist: notebook ; extra == 'extra'
